[
  {
    "date": "2025-06-12",
    "time": "16:31:00",
    "odd": 3
  },
  {
    "date": "2025-06-12",
    "time": "16:32:00",
    "odd": 3
  },
  {
    "date": "2025-06-12",
    "time": "16:34:00",
    "odd": 3
  },
  {
    "date": "2025-06-12",
    "time": "16:37:00",
    "odd": 3
  },
  {
    "date": "2025-06-12",
    "time": "16:39:00",
    "odd": 3
  },
  {
    "date": "2025-06-12",
    "time": "16:42:00",
    "odd": 3
  },
  {
    "date": "2025-06-12",
    "time": "16:44:00",
    "odd": 4
  }
]